{
  "version": "0.2",
  "language": "en",
  "words": [
    "VESUVIO",
    "Vesuvius",
    "Naples",
    "Napoli",
    "Napule",
    "Neapolitan",
    "Camorra",
    "Cosa",
    "Nostra",
    "Suburra",
    "Carabinieri",
    "Polizia",
    "Questura",
    "Questore",
    "Commissario",
    "Tribunale",
    "Giudice",
    "Parroco",
    "Affiliati",
    "Famiglia",
    "Capizona",
    "Sottocapo",
    "Prestanome",
    "paranza",
    "paranze",
    "pentito",
    "pentiti",
    "pizzo",
    "rione",
    "rioni",
    "Rione's",
    "quartieri",
    "mercato",
    "Lungomare",
    "Molo",
    "motorini",
    "sopra",
    "sotto",
    "Sant'Antonio",
    "Natale",
    "Pasqua",
    "Don",
    "Ranieri",
    "Ranieri's",
    "Ranieris",
    "Esposito",
    "Esposito's",
    "Domenico",
    "Domenico's",
    "Assunta",
    "Assunta's",
    "Fusco",
    "Gennaro",
    "Gennaro's",
    "Bianca",
    "Nunzio",
    "Nunzio's",
    "Fabiana",
    "Fabiana's",
    "Sarno",
    "Sarno's",
    "Renata",
    "Peppino",
    "Peppino's",
    "Iervolino",
    "Pietro",
    "Pietro's",
    "Mimì",
    "Vittoria",
    "Antò",
    "Amato",
    "Bacala",
    "Woodhaven",
    "Trône",
    "D'Angelo",
    "Ciprian",
    "Plesca",
    "Plesca's",
    "Stefano",
    "LocalPulse",
    "AgentFlow",
    "agentflowenterprise",
    "GitHub",
    "PitchDeck",
    "WorldBible",
    "StoryBible",
    "Moodbook",
    "BeatSheet",
    "Screenplay",
    "screenplay",
    "screenwriting",
    "Showrunner",
    "showrunner",
    "CrimeDrama",
    "crimefiction",
    "CharacterBible",
    "worldbuilding",
    "storytelling",
    "storyverse",
    "storyworld",
    "storylines",
    "storyarc",
    "transmedia",
    "underboss",
    "cinematography",
    "filmmaking",
    "canon",
    "lore",
    "worldmap",
    "bio",
    "mockups",
    "wordmark",
    "Logline",
    "Throughline",
    "throughlines",
    "arthouse",
    "Berlinale",
    "Biennale",
    "Canneseries",
    "comparables",
    "hander",
    "safehouse",
    "multigenerational",
    "businesspeople",
    "explorative",
    "dramatizable",
    "recontextualize",
    "recontextualizes",
    "recontextualizing",
    "aestheticize",
    "fetishizing",
    "mediatized",
    "unglamorized",
    "unshowy",
    "overcorrecting",
    "overcorrects",
    "underexploited",
    "underexplored",
    "interiority",
    "performatively",
    "Narratively",
    "desaturated",
    "accelerants",
    "IBAN",
    "SEPA",
    "CMFGUS",
    "LXXX",
    "adda",
    "abbrucia",
    "accatta",
    "arrete",
    "bbuono",
    "campà",
    "cchiù",
    "cetta",
    "Chello",
    "Chesta",
    "chesto",
    "chiagnere",
    "Chiamma",
    "chianto",
    "chiaro",
    "coperto",
    "corve",
    "criatura",
    "cumandammo",
    "cumminato",
    "degli",
    "diece",
    "diventare",
    "Doje",
    "dritto",
    "fede",
    "friddo",
    "fuoco",
    "Guagliune",
    "guagliò",
    "guagliό",
    "guaio",
    "jamme",
    "L'ombra",
    "l'onore",
    "legge",
    "lione",
    "maje",
    "manera",
    "morte",
    "mparato",
    "muorto",
    "Ncopp",
    "nire",
    "nisciuno",
    "Notte",
    "nuje",
    "Ogne",
    "pagà",
    "parla",
    "Passi",
    "perdona",
    "Piezzo",
    "piezzo",
    "Resta",
    "primmo",
    "prummesse",
    "putere",
    "rignà",
    "rimane",
    "Riunione",
    "rispetto",
    "rispietto",
    "salva",
    "Sanghe",
    "sanghe",
    "sconta",
    "scorda",
    "scuro",
    "SCUSA",
    "sempe",
    "sgarro",
    "sguardo",
    "silenzio",
    "simmo",
    "ssaje",
    "stanno",
    "Stato",
    "stessa",
    "sulo",
    "sultanto",
    "tene",
    "teniamoce",
    "tenimmoce",
    "tiempo",
    "torna",
    "tradisce",
    "Uagliù",
    "uocchie",
    "Verità",
    "Vero",
    "vulammo"
  ],
  "ignoreWords": [
    "lycheeverse",
    "Anson",
    "TRWIBEB1XXX",
    "TRWIGB2LXXX",
    "TRWI",
    "rwavxpu",
    "yffpanw",
    "bc1qf3yy0w8z37rwavxpu38wem3yffpanw7wzj32qj"
  ],
  "ignoreRegExpList": [
    "/`[a-zA-Z0-9]{20,}`/",
    "/\\b[a-zA-Z0-9]{25,}\\b/"
  ],
  "ignorePaths": [
    "node_modules/**",
    ".git/**",
    "assets/**",
    "*.pdf",
    "*.png",
    "*.jpg",
    "*.jpeg",
    "*.svg",
    "*.mp3",
    "*.mp4"
  ]
}
